hs_process/__init__.py
hs_process/batch.py
hs_process/segment.py
hs_process/spatial_mod.py
hs_process/spec_mod.py
hs_process/utilities.py
hs_process/data/Wells_rep2_20180628_16h56m_pika_gige_7_plot_611-cube-to-spec-mean.spec
hs_process/data/Wells_rep2_20180628_16h56m_pika_gige_7_plot_611-cube-to-spec-mean.spec.hdr
hs_process/data/Wells_rep2_20180628_16h56m_test_pika_gige_7-Convert Radiance Cube to Reflectance from Measured Reference Spectrum.bip
hs_process/data/Wells_rep2_20180628_16h56m_test_pika_gige_7-Convert Radiance Cube to Reflectance from Measured Reference Spectrum.bip.hdr
hs_process/data/micasense_rededge_3_band_response.csv
hs_process/data/sentera_6x_band_response.csv
hs_process/data/sentinel-2a_band_response.csv
hs_process/data/sentinel-2b_band_response.csv
hs_process/examples/tutorial_batch.ipynb
hs_process/examples/tutorial_hsio.ipynb
hs_process/examples/tutorial_hstools.ipynb
hs_process/examples/tutorial_segment.ipynb
hs_process/examples/tutorial_spatial_mod.ipynb
hs_process/examples/tutorial_spec_mod.ipynb
hs_process/tests/test.py
hs_process/tests/test_hsio.py
hs_process/tests/test_hsio.pyc
hs_process-0.0.4.dist-info/LICENSE
hs_process-0.0.4.dist-info/METADATA
hs_process-0.0.4.dist-info/WHEEL
hs_process-0.0.4.dist-info/top_level.txt
hs_process-0.0.4.dist-info/RECORD
