Metadata-Version: 2.1
Name: hs-process
Version: 0.0.4
Summary: An open-source Python package for geospatial processing of aerial hyperspectral imagery
Home-page: https://github.com/tnigon/hs_process
Author: Tyler J. Nigon
Author-email: nigo0024@umn.edu
License: MIT
Platform: UNKNOWN
Classifier: Development Status :: 4 - Beta
Classifier: Intended Audience :: Science/Research
Classifier: Natural Language :: English
Classifier: Operating System :: Microsoft :: Windows
Classifier: Programming Language :: Python :: 3
Requires-Dist: geopandas
Requires-Dist: seaborn
Requires-Dist: spectral
Requires-Dist: tqdm
